pyqwe_extra_dotenv/__init__.py
pyqwe_extra_dotenv-0.2.1.dist-info/LICENSE
pyqwe_extra_dotenv-0.2.1.dist-info/WHEEL
pyqwe_extra_dotenv-0.2.1.dist-info/METADATA
pyqwe_extra_dotenv-0.2.1.dist-info/RECORD
